{"data_mtime":1720011582,"dep_lines":[5,21,22,2,4,1,1,1,1,1,1,1,1,1,1,1,1,1,1,1,1,1],"dep_prios":[5,5,5,5,5,10,5,20,20,30,30,30,30,30,30,30,30,30,30,30,30,30],"dependencies":["redis.commands.timeseries.commands","redis.commands.timeseries.info","redis.commands.timeseries.utils","redis._parsers.helpers","redis.commands.helpers","redis","builtins","pyexpat.model","pyexpat.errors","_collections_abc","_typeshed","abc","redis._parsers","redis.client","redis.cluster","redis.commands.cluster","redis.commands.core","redis.commands.redismodules","redis.commands.sentinel","redis.typing","typing","typing_extensions"],"hash":"824cfac2c844cf3410af204e9eb02aa90cedb52f801df5e6b8dfc7d49dfc11b3","id":"redis.commands.timeseries","ignore_all":true,"interface_hash":"16a4623a20afdb5959b6b484d4004fe373a6e1e4932d967e3aaa0e48b273abe3","mtime":1716403644,"options":{"allow_redefinition":false,"allow_untyped_globals":false,"always_false":[],"always_true":[],"bazel":false,"check_untyped_defs":true,"disable_bytearray_promotion":false,"disable_error_code":["misc"],"disable_memoryview_promotion":false,"disabled_error_codes":["misc"],"disallow_any_decorated":false,"disallow_any_explicit":false,"disallow_any_expr":false,"disallow_any_generics":true,"disallow_any_unimported":false,"disallow_incomplete_defs":true,"disallow_subclassing_any":true,"disallow_untyped_calls":true,"disallow_untyped_decorators":true,"disallow_untyped_defs":true,"enable_error_code":[],"enabled_error_codes":[],"extra_checks":true,"follow_imports":"normal","follow_imports_for_stubs":false,"ignore_errors":false,"ignore_missing_imports":true,"implicit_optional":true,"implicit_reexport":false,"local_partial_types":false,"mypyc":false,"old_type_inference":false,"platform":"linux","plugins":[],"strict_concatenate":false,"strict_equality":true,"strict_optional":true,"warn_no_return":true,"warn_return_any":true,"warn_unreachable":false,"warn_unused_ignores":true},"path":"/home/robin/werk/Eigen/typedal/venv/lib/python3.10/site-packages/redis/commands/timeseries/__init__.py","plugin_data":null,"size":3459,"suppressed":[],"version_id":"1.10.1"}