{"data_mtime":1700580393,"dep_lines":[27,4,6,7,8,9,10,1,1],"dep_prios":[5,5,10,10,10,5,5,5,30],"dependencies":["pluggy._result","__future__","inspect","sys","warnings","types","typing","builtins","abc"],"hash":"4e218bb420026f46d3efbcadfcaa337b77af4c06664c4dd783f4fc02d05a03d5","id":"pluggy._hooks","ignore_all":true,"interface_hash":"4cbb4024dfac3ec969233880e072f82c5489094c07acdf4f98e6dd9eae948fd1","mtime":1698230609,"options":{"allow_redefinition":false,"allow_untyped_globals":false,"always_false":[],"always_true":[],"bazel":false,"check_untyped_defs":true,"disable_bytearray_promotion":false,"disable_error_code":[],"disable_memoryview_promotion":false,"disabled_error_codes":[],"disallow_any_decorated":false,"disallow_any_explicit":false,"disallow_any_expr":false,"disallow_any_generics":true,"disallow_any_unimported":false,"disallow_incomplete_defs":true,"disallow_subclassing_any":true,"disallow_untyped_calls":true,"disallow_untyped_decorators":true,"disallow_untyped_defs":true,"enable_error_code":[],"enabled_error_codes":[],"extra_checks":true,"follow_imports":"normal","follow_imports_for_stubs":false,"ignore_errors":false,"ignore_missing_imports":true,"implicit_optional":true,"implicit_reexport":false,"local_partial_types":false,"mypyc":false,"old_type_inference":false,"platform":"linux","plugins":[],"strict_concatenate":false,"strict_equality":true,"strict_optional":true,"warn_no_return":true,"warn_return_any":true,"warn_unreachable":false,"warn_unused_ignores":true},"path":"/home/robin/werk/Eigen/typedal/venv/lib/python3.11/site-packages/pluggy/_hooks.py","plugin_data":null,"size":23877,"suppressed":[],"version_id":"1.7.0"}