{"data_mtime":1700580394,"dep_lines":[3,15,16,17,27,1,3,4,5,6,7,15,1,1],"dep_prios":[10,10,5,5,5,5,20,10,10,10,5,20,5,30],"dependencies":["importlib.metadata","pluggy._tracing","pluggy._callers","pluggy._hooks","pluggy._result","__future__","importlib","inspect","types","warnings","typing","pluggy","builtins","abc"],"hash":"7dc614ed5111d02a654729b88c027b44215897a71f0d2795339f3d6071f1f6e0","id":"pluggy._manager","ignore_all":true,"interface_hash":"541e1db4e1cf48508c0cda4cf0f4f46f0b925f926eedcfc6a79219a2935c7b92","mtime":1698230609,"options":{"allow_redefinition":false,"allow_untyped_globals":false,"always_false":[],"always_true":[],"bazel":false,"check_untyped_defs":true,"disable_bytearray_promotion":false,"disable_error_code":[],"disable_memoryview_promotion":false,"disabled_error_codes":[],"disallow_any_decorated":false,"disallow_any_explicit":false,"disallow_any_expr":false,"disallow_any_generics":true,"disallow_any_unimported":false,"disallow_incomplete_defs":true,"disallow_subclassing_any":true,"disallow_untyped_calls":true,"disallow_untyped_decorators":true,"disallow_untyped_defs":true,"enable_error_code":[],"enabled_error_codes":[],"extra_checks":true,"follow_imports":"normal","follow_imports_for_stubs":false,"ignore_errors":false,"ignore_missing_imports":true,"implicit_optional":true,"implicit_reexport":false,"local_partial_types":false,"mypyc":false,"old_type_inference":false,"platform":"linux","plugins":[],"strict_concatenate":false,"strict_equality":true,"strict_optional":true,"warn_no_return":true,"warn_return_any":true,"warn_unreachable":false,"warn_unused_ignores":true},"path":"/home/robin/werk/Eigen/typedal/venv/lib/python3.11/site-packages/pluggy/_manager.py","plugin_data":null,"size":19517,"suppressed":[],"version_id":"1.7.0"}